counter.v
`timescale 1ns / 1ps

module counter #(
    parameter N = 8 // Default counter width is 8 bits
) (
    input wire clk,
    input wire rst_n, // Active-low asynchronous reset
    input wire [1:0] control,
    input wire [N-1:0] parallel_in,
    output reg [N-1:0] count_out
);

    // Sequential logic block
    always @(posedge clk or negedge rst_n) begin
        if (!rst_n) begin
            count_out <= {N{1'b0}}; // Reset counter to 0
        end else begin
            case (control)
                // 2'b00: Hold current state
                2'b00: count_out <= count_out;

                // 2'b01: Count up
                2'b01: count_out <= count_out + 1;

                // 2'b10: Count down
                2'b10: count_out <= count_out - 1;

                // 2'b11: Parallel Load
                2'b11: count_out <= parallel_in;

                // Default case to prevent latches in combinational logic,
                // though not strictly necessary here, it's good practice.
                default: count_out <= count_out;
            endcase
        end
    end

endmodule

tb_counter.v
`timescale 1ns / 1ps

module tb_counter;

    // Parameters
    localparam N = 16;
    localparam CLK_PERIOD = 10; // 10 ns clock period -> 100 MHz

    // Testbench signals
    reg clk;
    reg rst_n;
    reg [1:0] control;
    reg [N-1:0] parallel_in;
    wire [N-1:0] count_out;
    
    // Signals for file reading and checking
    integer file_handle;
    integer scan_status; // We will reuse this for $fgets
    reg [N-1:0] expected_out;
    integer error_count = 0;
    integer vector_count = 0;
    reg [1023:0] dummy_line;

    // Instantiate the Device Under Test (DUT)
    counter #(
        .N(N)
    ) dut (
        .clk(clk),
        .rst_n(rst_n),
        .control(control),
        .parallel_in(parallel_in),
        .count_out(count_out)
    );

    // Clock generator
    always #(CLK_PERIOD / 2) clk = ~clk;

    // Main simulation sequence
    initial begin
        // 1. Initialize signals and open vector file
        clk = 0;
        rst_n = 1;
        control = 2'b00;
        parallel_in = {N{1'b0}};

        file_handle = $fopen("test_vectors.txt", "r");
        if (file_handle == 0) begin
            $display("ERROR: Could not open test_vectors.txt");
            $finish;
        end

        // 2. Dump waves for GTKWave
        $dumpfile("counter_wave.vcd");
        $dumpvars(0, tb_counter);

        // 3. Apply reset
        rst_n = 0;
        #(CLK_PERIOD * 2);
        rst_n = 1;
        #(CLK_PERIOD);
        
        // *** THE FIX: Assign the return value of the $fgets function ***
        // $fgets returns the number of characters read, which we store in scan_status.
        scan_status = $fgets(dummy_line, file_handle);

        // 4. Main test loop
        $display("------ Starting Simulation ------");
        while (!$feof(file_handle)) begin
            scan_status = $fscanf(file_handle, "%b %b %b\n", control, parallel_in, expected_out);

            // Wait for the next clock edge
            @(posedge clk);
            
            #1; 
            if (count_out !== expected_out) begin
                $display("ERROR @ time %0t: Vector %0d", $time, vector_count);
                $display("  Control=%b, P_in=%b", control, parallel_in);
                $display("  Expected=%d, Got=%d", expected_out, count_out);
                error_count = error_count + 1;
            end
            vector_count = vector_count + 1;
        end

        // 5. Final report
        #(CLK_PERIOD);
        if (error_count == 0) begin
            $display("------ Simulation SUCCESS: All %0d tests passed! ------", vector_count);
        end else begin
            $display("------ Simulation FAILED: %0d errors out of %0d tests. ------", error_count, vector_count);
        end

        $fclose(file_handle);
        $finish;
    end

endmodule

counter_wave.vcd
$date
	Mon Sep 15 01:11:39 2025
$end
$version
	Icarus Verilog
$end
$timescale
	1ps
$end
$scope module tb_counter $end
$var wire 16 ! count_out [15:0] $end
$var parameter 32 " CLK_PERIOD $end
$var parameter 32 # N $end
$var reg 1 $ clk $end
$var reg 2 % control [1:0] $end
$var reg 1024 & dummy_line [1023:0] $end
$var reg 16 ' expected_out [15:0] $end
$var reg 16 ( parallel_in [15:0] $end
$var reg 1 ) rst_n $end
$var integer 32 * error_count [31:0] $end
$var integer 32 + file_handle [31:0] $end
$var integer 32 , scan_status [31:0] $end
$var integer 32 - vector_count [31:0] $end
$scope module dut $end
$var wire 1 $ clk $end
$var wire 2 . control [1:0] $end
$var wire 16 / parallel_in [15:0] $end
$var wire 1 ) rst_n $end
$var parameter 32 0 N $end
$var reg 16 1 count_out [15:0] $end
$upscope $end
$upscope $end
$enddefinitions $end
$comment Show the parameter values. $end
$dumpall
b10000 0
b10000 #
b1010 "
$end
#0
$dumpvars
b0 1
b0 /
b0 .
b0 -
bx ,
b10000000000000000000000000000011 +
b0 *
0)
b0 (
bx '
bx &
b0 %
0$
b0 !
$end
#5000
1$
#10000
0$
#15000
1$
#20000
0$
1)
#25000
1$
#30000
0$
b101010 '
b101010 (
b101010 /
b11 %
b11 .
b11 ,
b1011110010111100100000010101000110010101110011011101000010000001110110011001010110001101110100011011110111001001110011001110100010000001100011011011110110111001110100011100100110111101101100010110110011000100111010001100000101110100100000011100000110000101110010011000010110110001101100011001010110110001011111011010010110111001011011010011100010110100110001001110100011000001011101001000000110010101111000011100000110010101100011011101000110010101100100010111110110111101110101011101000101101101001110001011010011000100111010001100000101110100001010 &
#35000
b101010 !
b101010 1
1$
#36000
b0 (
b0 /
b0 %
b0 .
b1 -
#40000
0$
#45000
1$
#46000
b101011 '
b1 %
b1 .
b10 -
#50000
0$
#55000
b101011 !
b101011 1
1$
#56000
b101010 '
b10 %
b10 .
b11 -
#60000
0$
#65000
b101010 !
b101010 1
1$
#66000
b11010111110010 '
b11010111110010 (
b11010111110010 /
b11 %
b11 .
b100 -
#70000
0$
#75000
b11010111110010 !
b11010111110010 1
1$
#76000
b1110011011000101 (
b1110011011000101 /
b0 %
b0 .
b101 -
#80000
0$
#85000
1$
#86000
b1101011100011101 (
b1101011100011101 /
b110 -
#90000
0$
#95000
1$
#96000
b10010000000110 '
b10010000000110 (
b10010000000110 /
b11 %
b11 .
b111 -
#100000
0$
#105000
b10010000000110 !
b10010000000110 1
1$
#106000
b1010100010100111 '
b1010100010100111 (
b1010100010100111 /
b1000 -
#110000
0$
#115000
b1010100010100111 !
b1010100010100111 1
1$
#116000
b1010100010100110 '
b1111001101001000 (
b1111001101001000 /
b10 %
b10 .
b1001 -
#120000
0$
#125000
b1010100010100110 !
b1010100010100110 1
1$
#126000
b1010100010100111 '
b101000000111110 (
b101000000111110 /
b1 %
b1 .
b1010 -
#130000
0$
#135000
b1010100010100111 !
b1010100010100111 1
1$
#136000
b1010100010100110 '
b101100100010 (
b101100100010 /
b10 %
b10 .
b1011 -
#140000
0$
#145000
b1010100010100110 !
b1010100010100110 1
1$
#146000
b1010100010100111 '
b10000101111 (
b10000101111 /
b1 %
b1 .
b1100 -
#150000
0$
#155000
b1010100010100111 !
b1010100010100111 1
1$
#156000
b1010100010101000 '
b100011101100111 (
b100011101100111 /
b1101 -
#160000
0$
#165000
b1010100010101000 !
b1010100010101000 1
1$
#166000
b110100111001011 '
b110100111001011 (
b110100111001011 /
b11 %
b11 .
b1110 -
#170000
0$
#175000
b110100111001011 !
b110100111001011 1
1$
#176000
b10010101011 '
b10010101011 (
b10010101011 /
b1111 -
#180000
0$
#185000
b10010101011 !
b10010101011 1
1$
#186000
b10010101100 '
b111100111101100 (
b111100111101100 /
b1 %
b1 .
b10000 -
#190000
0$
#195000
b10010101100 !
b10010101100 1
1$
#196000
b10010101011 '
b1100010100000 (
b1100010100000 /
b10 %
b10 .
b10001 -
#200000
0$
#205000
b10010101011 !
b10010101011 1
1$
#206000
b10010101010 '
b111010010011001 (
b111010010011001 /
b10010 -
#210000
0$
#215000
b10010101010 !
b10010101010 1
1$
#216000
b10010101011 '
b1001011101111010 (
b1001011101111010 /
b1 %
b1 .
b10011 -
#220000
0$
#225000
b10010101011 !
b10010101011 1
1$
#226000
b10010101010 '
b1001011000010111 (
b1001011000010111 /
b10 %
b10 .
b10100 -
#230000
0$
#235000
b10010101010 !
b10010101010 1
1$
#236000
b10010101001 '
b1110000100010011 (
b1110000100010011 /
b10101 -
#240000
0$
#245000
b10010101001 !
b10010101001 1
1$
#246000
b10010101000 '
b1101011010001100 (
b1101011010001100 /
b10110 -
#250000
0$
#255000
b10010101000 !
b10010101000 1
1$
#256000
b100110111010101 (
b100110111010101 /
b0 %
b0 .
b10111 -
#260000
0$
#265000
1$
#266000
b100101011110110 (
b100101011110110 /
b11000 -
#270000
0$
#275000
1$
#276000
b11111110101110 (
b11111110101110 /
b11001 -
#280000
0$
#285000
1$
#286000
b10010100111 '
b1011000111100111 (
b1011000111100111 /
b10 %
b10 .
b11010 -
#290000
0$
#295000
b10010100111 !
b10010100111 1
1$
#296000
b10010101000 '
b11110011011110 (
b11110011011110 /
b1 %
b1 .
b11011 -
#300000
0$
#305000
b10010101000 !
b10010101000 1
1$
#306000
b10010101001 '
b1101001111110010 (
b1101001111110010 /
b11100 -
#310000
0$
#315000
b10010101001 !
b10010101001 1
1$
#316000
b10010101010 '
b110100010011110 (
b110100010011110 /
b11101 -
#320000
0$
#325000
b10010101010 !
b10010101010 1
1$
#326000
b1111001000010000 '
b1111001000010000 (
b1111001000010000 /
b11 %
b11 .
b11110 -
#330000
0$
#335000
b1111001000010000 !
b1111001000010000 1
1$
#336000
b1111001000010001 '
b101000010001 (
b101000010001 /
b1 %
b1 .
b11111 -
#340000
0$
#345000
b1111001000010001 !
b1111001000010001 1
1$
#346000
b1111001000010010 '
b1001101000101100 (
b1001101000101100 /
b100000 -
#350000
0$
#355000
b1111001000010010 !
b1111001000010010 1
1$
#356000
b1101001100110010 '
b1101001100110010 (
b1101001100110010 /
b11 %
b11 .
b100001 -
#360000
0$
#365000
b1101001100110010 !
b1101001100110010 1
1$
#366000
b1101001100110001 '
b100010100010000 (
b100010100010000 /
b10 %
b10 .
b100010 -
#370000
0$
#375000
b1101001100110001 !
b1101001100110001 1
1$
#376000
b1000111010001001 (
b1000111010001001 /
b0 %
b0 .
b100011 -
#380000
0$
#385000
1$
#386000
b1101001100110010 '
b11111100010000 (
b11111100010000 /
b1 %
b1 .
b100100 -
#390000
0$
#395000
b1101001100110010 !
b1101001100110010 1
1$
#396000
b1000101011110011 (
b1000101011110011 /
b0 %
b0 .
b100101 -
#400000
0$
#405000
1$
#406000
b10000011010010 '
b10000011010010 (
b10000011010010 /
b11 %
b11 .
b100110 -
#410000
0$
#415000
b10000011010010 !
b10000011010010 1
1$
#416000
b10000011010001 '
b110110100100101 (
b110110100100101 /
b10 %
b10 .
b100111 -
#420000
0$
#425000
b10000011010001 !
b10000011010001 1
1$
#426000
b1010110000001010 (
b1010110000001010 /
b0 %
b0 .
b101000 -
#430000
0$
#435000
1$
#436000
b10011100000000 '
b10011100000000 (
b10011100000000 /
b11 %
b11 .
b101001 -
#440000
0$
#445000
b10011100000000 !
b10011100000000 1
1$
#446000
b1001110010011110 '
b1001110010011110 (
b1001110010011110 /
b101010 -
#450000
0$
#455000
b1001110010011110 !
b1001110010011110 1
1$
#456000
b1010010001000 (
b1010010001000 /
b0 %
b0 .
b101011 -
#460000
0$
#465000
1$
#466000
b1111010111111000 '
b1111010111111000 (
b1111010111111000 /
b11 %
b11 .
b101100 -
#470000
0$
#475000
b1111010111111000 !
b1111010111111000 1
1$
#476000
b1111010111111001 '
b1101001100110010 (
b1101001100110010 /
b1 %
b1 .
b101101 -
#480000
0$
#485000
b1111010111111001 !
b1111010111111001 1
1$
#486000
b1111010111111010 '
b1100100110001100 (
b1100100110001100 /
b101110 -
#490000
0$
#495000
b1111010111111010 !
b1111010111111010 1
1$
#496000
b1100111111011110 '
b1100111111011110 (
b1100111111011110 /
b11 %
b11 .
b101111 -
#500000
0$
#505000
b1100111111011110 !
b1100111111011110 1
1$
#506000
b1111011101110110 '
b1111011101110110 (
b1111011101110110 /
b110000 -
#510000
0$
#515000
b1111011101110110 !
b1111011101110110 1
1$
#516000
b1111011101110111 '
b1000100011001001 (
b1000100011001001 /
b1 %
b1 .
b110001 -
#520000
0$
#525000
b1111011101110111 !
b1111011101110111 1
1$
#526000
b1111011101111000 '
b1010110010000001 (
b1010110010000001 /
b110010 -
#530000
0$
#535000
b1111011101111000 !
b1111011101111000 1
1$
#536000
b1111101111110010 (
b1111101111110010 /
b0 %
b0 .
b110011 -
#540000
0$
#545000
1$
#546000
b1111011101111001 '
b10110001000 (
b10110001000 /
b1 %
b1 .
b110100 -
#550000
0$
#555000
b1111011101111001 !
b1111011101111001 1
1$
#556000
b1001010000111 (
b1001010000111 /
b0 %
b0 .
b110101 -
#560000
0$
#565000
1$
#566000
b1111011101111000 '
b101101110000101 (
b101101110000101 /
b10 %
b10 .
b110110 -
#570000
0$
#575000
b1111011101111000 !
b1111011101111000 1
1$
#576000
b1101000011011100 '
b1101000011011100 (
b1101000011011100 /
b11 %
b11 .
b110111 -
#580000
0$
#585000
b1101000011011100 !
b1101000011011100 1
1$
#586000
b1101000011011101 '
b11001111111100 (
b11001111111100 /
b1 %
b1 .
b111000 -
#590000
0$
#595000
b1101000011011101 !
b1101000011011101 1
1$
#596000
b11110110110010 (
b11110110110010 /
b0 %
b0 .
b111001 -
#600000
0$
#605000
1$
#606000
b1101000011011110 '
b111001010011100 (
b111001010011100 /
b1 %
b1 .
b111010 -
#610000
0$
#615000
b1101000011011110 !
b1101000011011110 1
1$
#616000
b11101100111 '
b11101100111 (
b11101100111 /
b11 %
b11 .
b111011 -
#620000
0$
#625000
b11101100111 !
b11101100111 1
1$
#626000
b11101100110 '
b1110100011100 (
b1110100011100 /
b10 %
b10 .
b111100 -
#630000
0$
#635000
b11101100110 !
b11101100110 1
1$
#636000
b11101100101 '
b10101110100111 (
b10101110100111 /
b111101 -
#640000
0$
#645000
b11101100101 !
b11101100101 1
1$
#646000
b111000101111101 '
b111000101111101 (
b111000101111101 /
b11 %
b11 .
b111110 -
#650000
0$
#655000
b111000101111101 !
b111000101111101 1
1$
#656000
b111000101111110 '
b1000010111001010 (
b1000010111001010 /
b1 %
b1 .
b111111 -
#660000
0$
#665000
b111000101111110 !
b111000101111110 1
1$
#666000
b111000101111101 '
b100110010011000 (
b100110010011000 /
b10 %
b10 .
b1000000 -
#670000
0$
#675000
b111000101111101 !
b111000101111101 1
1$
#676000
b111000101111110 '
b1010111100001001 (
b1010111100001001 /
b1 %
b1 .
b1000001 -
#680000
0$
#685000
b111000101111110 !
b111000101111110 1
1$
#686000
b111000101111111 '
b11001011011001 (
b11001011011001 /
b1000010 -
#690000
0$
#695000
b111000101111111 !
b111000101111111 1
1$
#696000
b1001101000001100 '
b1001101000001100 (
b1001101000001100 /
b11 %
b11 .
b1000011 -
#700000
0$
#705000
b1001101000001100 !
b1001101000001100 1
1$
#706000
b110000010111000 '
b110000010111000 (
b110000010111000 /
b1000100 -
#710000
0$
#715000
b110000010111000 !
b110000010111000 1
1$
#716000
b110000010111001 '
b1110001101110111 (
b1110001101110111 /
b1 %
b1 .
b1000101 -
#720000
0$
#725000
b110000010111001 !
b110000010111001 1
1$
#726000
b1111100001101 (
b1111100001101 /
b0 %
b0 .
b1000110 -
#730000
0$
#735000
1$
#736000
b110000010111010 '
b1110100101100010 (
b1110100101100010 /
b1 %
b1 .
b1000111 -
#740000
0$
#745000
b110000010111010 !
b110000010111010 1
1$
#746000
b1011001110010010 (
b1011001110010010 /
b0 %
b0 .
b1001000 -
#750000
0$
#755000
1$
#756000
b10001011001011 (
b10001011001011 /
b1001001 -
#760000
0$
#765000
1$
#766000
b1010100000001001 '
b1010100000001001 (
b1010100000001001 /
b11 %
b11 .
b1001010 -
#770000
0$
#775000
b1010100000001001 !
b1010100000001001 1
1$
#776000
b11010100000000 '
b11010100000000 (
b11010100000000 /
b1001011 -
#780000
0$
#785000
b11010100000000 !
b11010100000000 1
1$
#786000
b1000100111001001 '
b1000100111001001 (
b1000100111001001 /
b1001100 -
#790000
0$
#795000
b1000100111001001 !
b1000100111001001 1
1$
#796000
b1111010100000100 '
b1111010100000100 (
b1111010100000100 /
b1001101 -
#800000
0$
#805000
b1111010100000100 !
b1111010100000100 1
1$
#806000
b11100011100100 (
b11100011100100 /
b0 %
b0 .
b1001110 -
#810000
0$
#815000
1$
#816000
b1100110001110100 (
b1100110001110100 /
b1001111 -
#820000
0$
#825000
1$
#826000
b1111010100000101 '
b101110010011001 (
b101110010011001 /
b1 %
b1 .
b1010000 -
#830000
0$
#835000
b1111010100000101 !
b1111010100000101 1
1$
#836000
b1111010100000100 '
b1011100100010 (
b1011100100010 /
b10 %
b10 .
b1010001 -
#840000
0$
#845000
b1111010100000100 !
b1111010100000100 1
1$
#846000
b110100101101001 '
b110100101101001 (
b110100101101001 /
b11 %
b11 .
b1010010 -
#850000
0$
#855000
b110100101101001 !
b110100101101001 1
1$
#856000
b1000011101101000 (
b1000011101101000 /
b0 %
b0 .
b1010011 -
#860000
0$
#865000
1$
#866000
b110010110111111 '
b110010110111111 (
b110010110111111 /
b11 %
b11 .
b1010100 -
#870000
0$
#875000
b110010110111111 !
b110010110111111 1
1$
#876000
b1011010111101110 '
b1011010111101110 (
b1011010111101110 /
b1010101 -
#880000
0$
#885000
b1011010111101110 !
b1011010111101110 1
1$
#886000
b1011010111101101 '
b1000110011111101 (
b1000110011111101 /
b10 %
b10 .
b1010110 -
#890000
0$
#895000
b1011010111101101 !
b1011010111101101 1
1$
#896000
b101111101100010 (
b101111101100010 /
b0 %
b0 .
b1010111 -
#900000
0$
#905000
1$
#906000
b1110101110001 (
b1110101110001 /
b1011000 -
#910000
0$
#915000
1$
#916000
b1011010111101110 '
b110111101110110 (
b110111101110110 /
b1 %
b1 .
b1011001 -
#920000
0$
#925000
b1011010111101110 !
b1011010111101110 1
1$
#926000
b11000011000110 (
b11000011000110 /
b0 %
b0 .
b1011010 -
#930000
0$
#935000
1$
#936000
b1011010111101111 '
b100101011100101 (
b100101011100101 /
b1 %
b1 .
b1011011 -
#940000
0$
#945000
b1011010111101111 !
b1011010111101111 1
1$
#946000
b1011010111101110 '
b10110010110110 (
b10110010110110 /
b10 %
b10 .
b1011100 -
#950000
0$
#955000
b1011010111101110 !
b1011010111101110 1
1$
#956000
b1111100001110110 '
b1111100001110110 (
b1111100001110110 /
b11 %
b11 .
b1011101 -
#960000
0$
#965000
b1111100001110110 !
b1111100001110110 1
1$
#966000
b111000000100 (
b111000000100 /
b0 %
b0 .
b1011110 -
#970000
0$
#975000
1$
#976000
b101111111101001 '
b101111111101001 (
b101111111101001 /
b11 %
b11 .
b1011111 -
#980000
0$
#985000
b101111111101001 !
b101111111101001 1
1$
#986000
b1101100000110 '
b1101100000110 (
b1101100000110 /
b1100000 -
#990000
0$
#995000
b1101100000110 !
b1101100000110 1
1$
#996000
b1101100000111 '
b10011000101010 (
b10011000101010 /
b1 %
b1 .
b1100001 -
#1000000
0$
#1005000
b1101100000111 !
b1101100000111 1
1$
#1006000
b110000011101100 (
b110000011101100 /
b0 %
b0 .
b1100010 -
#1010000
0$
#1015000
1$
#1016000
b1101100001000 '
b1111000001010110 (
b1111000001010110 /
b1 %
b1 .
b1100011 -
#1020000
0$
#1025000
b1101100001000 !
b1101100001000 1
1$
#1026000
b1100100 -
#1030000
0$
#1035000
b1101100001001 !
b1101100001001 1
1$
